poetry_python_version/__init__.py
poetry_python_version/plugins.py
poetry_python_version-0.0.6.dist-info/LICENSE
poetry_python_version-0.0.6.dist-info/METADATA
poetry_python_version-0.0.6.dist-info/WHEEL
poetry_python_version-0.0.6.dist-info/entry_points.txt
poetry_python_version-0.0.6.dist-info/RECORD
