Metadata-Version: 2.1
Name: poetry-python-version
Version: 0.0.6
Summary: Poetry plugin to read Python version from .python-version file
Home-page: https://github.com/jirikuncar/poetry-python-version
License: MIT
Author: Jiri Kuncar
Author-email: jiri.kuncar@gmail.com
Classifier: License :: OSI Approved :: MIT License
Classifier: Programming Language :: Python :: 2
Classifier: Programming Language :: Python :: 2.7
Classifier: Programming Language :: Python :: 3
Classifier: Programming Language :: Python :: 3.4
Classifier: Programming Language :: Python :: 3.5
Classifier: Programming Language :: Python :: 3.6
Classifier: Programming Language :: Python :: 3.7
Classifier: Programming Language :: Python :: 3.8
Classifier: Programming Language :: Python :: 3.9
Classifier: Programming Language :: Python :: 3.10
Classifier: Programming Language :: Python :: 3.11
Requires-Dist: poetry (>=1.5,<2.0)
Project-URL: Repository, https://github.com/jirikuncar/poetry-python-version
